transient_display_data/__init__.py
transient_display_data/_version.py
transient_display_data-0.4.4.data/data/share/jupyter/labextensions/transient-display-data/build_log.json
transient_display_data-0.4.4.data/data/share/jupyter/labextensions/transient-display-data/package.json
transient_display_data-0.4.4.data/data/share/jupyter/labextensions/transient-display-data/static/lib_index_js.1e2dc1b3ae89daabd4a4.js
transient_display_data-0.4.4.data/data/share/jupyter/labextensions/transient-display-data/static/lib_index_js.1e2dc1b3ae89daabd4a4.js.map
transient_display_data-0.4.4.data/data/share/jupyter/labextensions/transient-display-data/static/remoteEntry.0ed960760553e36a5747.js
transient_display_data-0.4.4.data/data/share/jupyter/labextensions/transient-display-data/static/remoteEntry.0ed960760553e36a5747.js.map
transient_display_data-0.4.4.data/data/share/jupyter/labextensions/transient-display-data/static/style.js
transient_display_data-0.4.4.data/data/share/jupyter/labextensions/transient-display-data/static/style_index_js.7e69d2a770ce3df457b5.js
transient_display_data-0.4.4.data/data/share/jupyter/labextensions/transient-display-data/static/style_index_js.7e69d2a770ce3df457b5.js.map
transient_display_data-0.4.4.data/data/share/jupyter/labextensions/transient-display-data/install.json
transient_display_data-0.4.4.dist-info/METADATA
transient_display_data-0.4.4.dist-info/WHEEL
transient_display_data-0.4.4.dist-info/licenses/LICENSE
transient_display_data-0.4.4.dist-info/RECORD
