Metadata-Version: 2.1
Name: transient_display_data
Version: 0.4.4
Summary: Extension to display transient_display_data in Jupyter Lab
Project-URL: Homepage, https://github.com/vatlab/transient-display-data
Project-URL: Bug Tracker, https://github.com/vatlab/transient-display-data/issues
Project-URL: Repository, https://github.com/vatlab/transient-display-data.git
Author: Bo Peng
License: BSD 3-Clause License
License-File: LICENSE
Classifier: Framework :: Jupyter
Classifier: Framework :: Jupyter :: JupyterLab
Classifier: Framework :: Jupyter :: JupyterLab :: 4
Classifier: Framework :: Jupyter :: JupyterLab :: Extensions
Classifier: Framework :: Jupyter :: JupyterLab :: Extensions :: Prebuilt
Classifier: License :: OSI Approved :: BSD License
Classifier: Programming Language :: Python
Classifier: Programming Language :: Python :: 3
Classifier: Programming Language :: Python :: 3.8
Classifier: Programming Language :: Python :: 3.9
Classifier: Programming Language :: Python :: 3.10
Classifier: Programming Language :: Python :: 3.11
Requires-Python: >=3.8
